{
  "texto": "HILDA AUSTREBERTA ESCOBEDO OCAÑA\nO\nHILDA AUSTREBERTA ESCOBEDO.\n\nDURANTE LA REALIZACION DEL XI CONGRESO GENERAL\nEXTRAORDINARIO DEL SINDICATO INDEPENDIENTE DE TRABAJADO-\nRES DE LA UNIVERSIDAD AUTONOMA METROPOLITANA, QUE SE\nEFECTUO EN LA UNIDAD IZTAPALAPA DE LA UAM., UNA PERSONA--\nRESPONSABILIZO A LA SECRETARIA DE GOBERNACION Y A LA\nDGPYT, DEL D.F., DE LA DESAPARICION DE ESTA PERSONA DE--\nSU FUENTE DE TRABAJO.\nACAPULCO, GRO.-MIEMBROS DE LA ASOCIACION CIVI-\nCA GUERRERENSE, FIJARON PROPAGANDA EN DIFERENTES AVENI--\nDAS DEL PUERTO EN DONDE EXIGEN LA PRESENTACION DE ESTA\nPERSONA, DESAPARECIDA EL 31 DE DICIEMBRE DE 1981.\nEN LA PROPAGANDA QUE SE FIJO EN LA FACULTAD DE\nPSICOLOGIA, FIRMADA POR LA COORDINADORA NACIONAL PLAN DE\nAYALA (CNPA) Y LA ASOCIACION GUERRERENSE, SE EXIGE LA LI\nBERTAD DE ESA PERSONA.",
  "eventos": [
    {
      "tipo": "CAPTURA",
      "descripcion": "DESAPARICION DE ESTA PERSONA",
      "fecha": null,
      "lugar": "SU FUENTE DE TRABAJO",
      "victimas": [
        "HILDA AUSTREBERTA ESCOBEDO OCAÑA"
      ],
      "victimarios": [
        "SECRETARIA DE GOBERNACION",
        "DGPYT"
      ]
    },
    {
      "tipo": "CAPTURA",
      "descripcion": "DESAPARECIDA EL 31 DE DICIEMBRE DE 1981",
      "fecha": "31 DE DICIEMBRE DE 1981",
      "lugar": null,
      "victimas": [
        "HILDA AUSTREBERTA ESCOBEDO OCAÑA"
      ],
      "victimarios": []
    }
  ]
}